yoguido/__init__.py
yoguido/core/audit.py
yoguido/core/compiler.py
yoguido/core/decorators.py
yoguido/core/runtime.py
yoguido/core/state.py
yoguido/data/db.py
yoguido/examples/debug_buttons.py
yoguido/examples/debug_tools.py
yoguido/examples/demo_admin.py
yoguido/pages/routing.py
yoguido/server/app.py
yoguido/ui/basic_components.py
yoguido/ui/chart_components.py
yoguido/ui/components.py
yoguido/ui/data_components.py
yoguido/ui/form_components.py
yoguido/ui/layout_components.py
yoguido/ui/navigation_components.py
yoguido-0.1.11.dist-info/licenses/LICENSE
yoguido-0.1.11.dist-info/METADATA
yoguido-0.1.11.dist-info/WHEEL
yoguido-0.1.11.dist-info/entry_points.txt
yoguido-0.1.11.dist-info/top_level.txt
yoguido-0.1.11.dist-info/RECORD
